compressedfhir/__init__.py
compressedfhir/py.typed
compressedfhir/fhir/__init__.py
compressedfhir/fhir/base_resource_list.py
compressedfhir/fhir/fhir_bundle.py
compressedfhir/fhir/fhir_bundle_entry.py
compressedfhir/fhir/fhir_bundle_entry_list.py
compressedfhir/fhir/fhir_bundle_entry_request.py
compressedfhir/fhir/fhir_bundle_entry_response.py
compressedfhir/fhir/fhir_bundle_entry_search.py
compressedfhir/fhir/fhir_identifier.py
compressedfhir/fhir/fhir_link.py
compressedfhir/fhir/fhir_meta.py
compressedfhir/fhir/fhir_resource.py
compressedfhir/fhir/fhir_resource_list.py
compressedfhir/fhir/fhir_resource_map.py
compressedfhir/fhir/test/__init__.py
compressedfhir/fhir/test/test_bundle_entry.py
compressedfhir/fhir/test/test_bundle_entry_list.py
compressedfhir/fhir/test/test_bundle_entry_request.py
compressedfhir/fhir/test/test_bundle_entry_response.py
compressedfhir/fhir/test/test_fhir_bundle.py
compressedfhir/fhir/test/test_fhir_resource.py
compressedfhir/fhir/test/test_fhir_resource_list.py
compressedfhir/fhir/test/test_fhir_resource_map.py
compressedfhir/utilities/__init__.py
compressedfhir/utilities/fhir_json_encoder.py
compressedfhir/utilities/json_helpers.py
compressedfhir/utilities/compressed_dict/__init__.py
compressedfhir/utilities/compressed_dict/v1/__init__.py
compressedfhir/utilities/compressed_dict/v1/compressed_dict.py
compressedfhir/utilities/compressed_dict/v1/compressed_dict_access_error.py
compressedfhir/utilities/compressed_dict/v1/compressed_dict_storage_mode.py
compressedfhir/utilities/compressed_dict/v1/test/__init__.py
compressedfhir/utilities/compressed_dict/v1/test/test_compressed_dict.py
compressedfhir/utilities/json_serializers/__init__.py
compressedfhir/utilities/json_serializers/type_preservation_decoder.py
compressedfhir/utilities/json_serializers/type_preservation_encoder.py
compressedfhir/utilities/json_serializers/type_preservation_serializer.py
compressedfhir/utilities/json_serializers/test/__init__.py
compressedfhir-3.0.4.dist-info/licenses/LICENSE
compressedfhir-3.0.4.dist-info/METADATA
compressedfhir-3.0.4.dist-info/WHEEL
compressedfhir-3.0.4.dist-info/top_level.txt
compressedfhir-3.0.4.dist-info/RECORD
